{
    "version": "0.1",
    "date": [
        "2024.09.30",
        "2024.10.04"
    ],
    "list": [
        {
            "class7": {
                "Monday": [
                    {
                        "time": "15:00",
                        "middlelesson": "30m",
                        "text": "Фізика"
                    },
                    {
                        "time": "16:00",
                        "middlelesson": "30m",
                        "text": "Англійська мова"
                    },
                    {
                        "time": "17:00",
                        "middlelesson": "30m",
                        "text": "Здоров'я"
                    },
                    {
                        "time":"18:00",
                        "middlelesson":"30m",
                        "text":"Література"
                    }
                ],
                "Tuesday": [
                    {
                        "time": "15:00",
                        "middlelesson": "30m",
                        "text": "Фізика"
                    },
                    {
                        "time": "16:00",
                        "middlelesson": "30m",
                        "text": "Англійська мова"
                    },
                    {
                        "time":"17:00",
                        "middlelesson":"30m",
                        "text":"Здоров'я"
                    },
                    {
                        "time":"18:00",
                        "middlelesson":"30m",
                        "text":"Література"
                    }
                ],
                "Wednesday": [
                    {
                        "time": "14:00",
                        "middlelesson": "30m",
                        "text": "Географія"
                    },
                    {
                        "time": "15:00",
                        "middlelesson": "30m",
                        "text": "Алгебра"
                    },
                    {
                        "time": "16:00",
                        "middlelesson": "30m",
                        "text": "Фізична культура"
                    }
                ],
                "Thursday": [
                    {
                        "time": "14:00",
                        "middlelesson": "30m",
                        "text": "Англійська мова"
                    },
                    {
                        "time": "15:00",
                        "middlelesson": "30m",
                        "text": "Українська мова"
                    },
                    {
                        "time": "16:00",
                        "middlelesson": "30m",
                        "text": "Німецька"
                    }
                ],
                "Friday": [
                    {
                        "time": "14:00",
                        "middlelesson": "30m",
                        "text": "Технології"
                    },
                    {
                        "time": "15:00",
                        "middlelesson": "30m",
                        "text": "Історія"
                    },
                    {
                        "time": "16:00",
                        "middlelesson": "30m",
                        "text": "Література"
                    }
                ]
            }
        }
    ]
}
